narrator/__init__.py
narrator/database/__init__.py
narrator/database/cli.py
narrator/database/models.py
narrator/database/storage_backend.py
narrator/database/thread_store.py
narrator/database/migrations/__init__.py
narrator/models/__init__.py
narrator/models/attachment.py
narrator/models/message.py
narrator/models/thread.py
narrator/storage/__init__.py
narrator/storage/file_store.py
narrator/utils/__init__.py
narrator/utils/logging.py
slide_narrator-6.3.0.dist-info/METADATA
slide_narrator-6.3.0.dist-info/WHEEL
slide_narrator-6.3.0.dist-info/entry_points.txt
slide_narrator-6.3.0.dist-info/licenses/LICENSE
slide_narrator-6.3.0.dist-info/RECORD
