Metadata-Version: 2.4
Name: slide-narrator
Version: 6.3.0
Summary: Thread and file storage components for conversational AI - the companion to Tyler AI framework
Project-URL: Homepage, https://github.com/adamwdraper/slide
Project-URL: Repository, https://github.com/adamwdraper/slide
Project-URL: Bug Tracker, https://github.com/adamwdraper/slide/issues
Author: adamwdraper
License: MIT
License-File: LICENSE
Classifier: Development Status :: 3 - Alpha
Classifier: Intended Audience :: Developers
Classifier: License :: OSI Approved :: MIT License
Classifier: Operating System :: OS Independent
Classifier: Programming Language :: Python :: 3
Classifier: Programming Language :: Python :: 3.11
Classifier: Programming Language :: Python :: 3.12
Classifier: Programming Language :: Python :: 3.13
Requires-Python: >=3.11
Requires-Dist: aiosqlite>=0.21.0
Requires-Dist: alembic>=1.14.1
Requires-Dist: asyncpg>=0.30.0
Requires-Dist: click>=8.1.8
Requires-Dist: filetype>=1.2.0
Requires-Dist: greenlet>=3.2.3
Requires-Dist: pydantic>=2.10.4
Requires-Dist: pypdf>=5.3.0
Requires-Dist: sqlalchemy>=2.0.36
Requires-Dist: typing-extensions>=4.12.0
Provides-Extra: dev
Requires-Dist: coverage>=7.6.10; extra == 'dev'
Requires-Dist: pytest-asyncio>=0.25.2; extra == 'dev'
Requires-Dist: pytest-cov>=6.0.0; extra == 'dev'
Requires-Dist: pytest>=8.3.4; extra == 'dev'
